{"cameraMode":{"drawMode":0,"name":"Shaded","section":"Shading Mode"},"sceneLighting":true,"audioPlay":false,"sceneViewState":{"showFog":true,"showMaterialUpdate":false,"showSkybox":true,"showFlares":true,"showImageEffects":true,"showParticleSystems":true},"in2DMode":false,"pivot":{"x":0.06644894182682038,"y":3.862095594406128,"z":0.5648698806762695},"rotation":{"x":0.029641689732670785,"y":0.05454613268375397,"z":0.0016198033699765802,"w":-0.9980699419975281},"size":9.122214317321778,"orthographic":false}